[
  {
    "account": "WeirdCoffeePerson",
    "password": "HarioV60",
    "cellphone": "09677839204",
    "email": "qwefliblqerv@gmail.com",
    "userName": "James Hoffman",
    "creditCard": "0168226654878741"
  },
  {
    "account": "SunnyDay92",
    "password": "g83hBuea9snv",
    "cellphone": "09876543210",
    "email": "sunnyday92@example.com",
    "userName": "Emma Thompson",
    "creditCard": "5284196606022510"
  },
  {
    "account": "TechGuru21",
    "password": "p8aWs9YxUtN",
    "cellphone": "09123456789",
    "email": "techguru21@mail.com",
    "userName": "Daniel Johnson",
    "creditCard": "4629178085678743"
  },
  {
    "account": "ArtLover77",
    "password": "12jPqMvb32D1",
    "cellphone": "09456789012",
    "email": "artlover77@domain.com",
    "userName": "Sophia Roberts",
    "creditCard": "371449635398431"
  },
  {
    "account": "GamingNinja",
    "password": "Q86RcT25tS9",
    "cellphone": "09789012345",
    "email": "gamingninja99@hotmail.com",
    "userName": "Ryan Smith",
    "creditCard": "6011318436481018"
  },
  {
    "account": "Bookworm88",
    "password": "W29yuXu1aU4",
    "cellphone": "09543210987",
    "email": "bookworm88@gmail.com",
    "userName": "Olivia Davis",
    "creditCard": "4916115966535162"
  },
  {
    "account": "FoodieChef",
    "password": "7m1ZrN4eYg6",
    "cellphone": "09678901234",
    "email": "foodiechef@domain.com",
    "userName": "Emily Anderson",
    "creditCard": "5459243195108677"
  }
]